{
  "body":{
    "apkVersionCurrent":3,
    "dtStampSynk":1464936318182,"downloadUrl":"http://hsf.hanssem.com/Agencyweb/cube2/service_suwon_v9_v2.2.1_20160603_01.zip"
    //"dtStampSynk":1463131986379,"downloadUrl":"http://hsf.hanssem.com/Agencyweb/cube2/service_suwon_20160513_01.zip"
    //"dtStampSynk":1462345976805,"downloadUrl":"http://hsf.hanssem.com/Agencyweb/cube2/service_suwon_20160504_03.zip"
  },
  "head":{
    "command":"command",
    "deviceId":"000000",
    "dtStamp":1462168869937,
    "macaddress":"000000",
    "message":"message",
    "resultCode":"0"
  }
}
